{"nodes": [{"id": "graphify_out_graph_report_md", "label": "Graph extraction report (GRAPH_REPORT.md)", "file_type": "document", "source_file": "graphify-out/GRAPH_REPORT.md", "source_location": null, "source_url": null, "captured_at": null, "author": null, "contributor": null}], "edges": [{"source": "graphify_out_graph_html", "target": "graphify_out_graph_report_md", "relation": "references", "confidence": "EXTRACTED", "confidence_score": 1.0, "source_file": "graphify-out/GRAPH_REPORT.md", "source_location": null, "weight": 1.0}], "hyperedges": []}