{"nodes": [{"id": "public_hard_reload_html", "label": "hard-reload.html (cache-buster)", "file_type": "document", "source_file": "public/hard-reload.html", "source_location": null, "source_url": null, "captured_at": null, "author": null, "contributor": null}, {"id": "hard_reload_hardreload", "label": "hardReload()", "file_type": "document", "source_file": "public/hard-reload.html", "source_location": null, "source_url": null, "captured_at": null, "author": null, "contributor": null}], "edges": [{"source": "public_hard_reload_html", "target": "hard_reload_hardreload", "relation": "references", "confidence": "EXTRACTED", "confidence_score": 1.0, "source_file": "public/hard-reload.html", "source_location": null, "weight": 1.0}, {"source": "hard_reload_hardreload", "target": "sessionid_handler", "relation": "conceptually_related_to", "confidence": "INFERRED", "confidence_score": 0.6, "source_file": "public/hard-reload.html", "source_location": null, "weight": 0.6}], "hyperedges": []}